seqal/__init__.py
seqal/active_learner.py
seqal/aligner.py
seqal/data.py
seqal/datasets.py
seqal/performance_recorder.py
seqal/samplers/__init__.py
seqal/samplers/base.py
seqal/samplers/samplers.py
seqal/stoppers/__init__.py
seqal/stoppers/base.py
seqal/stoppers/stopper.py
seqal/tagger.py
seqal/transformer.py
seqal/utils.py
seqal-0.3.5.dist-info/LICENSE
seqal-0.3.5.dist-info/WHEEL
seqal-0.3.5.dist-info/METADATA
seqal-0.3.5.dist-info/RECORD
