Metadata-Version: 2.1
Name: seqal
Version: 0.3.5
Summary: Sequence labeling active learning framework for Python
Home-page: https://github.com/BrambleXu/seqal
License: MIT
Author: Xu Liang
Author-email: liangxu006@gmail.com
Requires-Python: >=3.8,<4.0
Classifier: Development Status :: 2 - Pre-Alpha
Classifier: Intended Audience :: Developers
Classifier: License :: OSI Approved :: MIT License
Classifier: Natural Language :: English
Classifier: Operating System :: OS Independent
Classifier: Programming Language :: Python :: 3
Classifier: Programming Language :: Python :: 3.10
Classifier: Programming Language :: Python :: 3.8
Classifier: Programming Language :: Python :: 3.9
Classifier: Topic :: Software Development :: Libraries
Provides-Extra: docs
Requires-Dist: flair (==0.10)
Requires-Dist: scipy (>=1.8.0,<2.0.0)
Requires-Dist: spacy (>=3.4.1,<4.0.0)
Requires-Dist: torch (>=1.10.0,<2.0.0)
Project-URL: Bug Tracker, https://github.com/BrambleXu/seqal/issues
Project-URL: Changelog, https://seqal.readthedocs.io/changelog.html
Project-URL: Documentation, https://seqal.readthedocs.io
Project-URL: Repository, https://github.com/BrambleXu/seqal
